pipelined_processor.v
module processor(input clk1,input clk2);
parameter ADD =6'd0,SUB=6'd1,AND=6'd2,OR=6'd3,SLT=6'd4,MUL=6'd5,HLT=6'b111111, // r type instructions
          LW=6'd8,SW=6'd9,ADDI=6'd10,SUBI=6'd11,SLTI=6'd12,BNEQZ=6'd13,BEQZ=6'd14;// i type instructions

    //FIRST STAGE
    reg [31:0] IF_ID_IR,PC,IF_ID_NPC;
    //SECOND STAGE
    reg[31:0] ID_EX_IR, ID_EX_A, ID_EX_B, ID_EX_IMM, ID_EX_NPC;

    reg[2:0] ID_EX_TYPE, EX_MEM_TYPE, MEM_WB_TYPE;

    //THIRD

    reg[31:0] EX_MEM_B, EX_MEM_IR, EX_MEM_ALUOUT;
    reg  EX_MEM_COND;

    // FOURTH

    reg[31:0] MEM_WB_ALUOUT, MEM_WB_LMD, MEM_WB_IR;

    reg [31:0] REG[0:31];// regbank
    reg [31:0] MEM[0:1023];// instruction memory

    parameter RR_ALU= 3'd0, RM_ALU=3'd1, LOAD=3'd2, STORE= 3'd3, BRANCH=3'd4,HALT=3'd5; // instruction types

    reg HALTED;// whenever an halt instruction is encountered it is set to one stop the execution of the program

    reg TAKEN_BRANCH;// set to one when a branch is taken


    always @(posedge clk1) begin //IF STAGE
        if(HALTED==0)begin

            if((EX_MEM_IR[31:26] ==  BEQZ && EX_MEM_COND == 1)||
            (EX_MEM_IR[31:26] == BNEQZ && EX_MEM_COND == 0)) begin

                TAKEN_BRANCH <= #2 1;
                IF_ID_IR <= #2 MEM[EX_MEM_ALUOUT];
                IF_ID_NPC <= #2 EX_MEM_ALUOUT+1;
                PC <= #2 EX_MEM_ALUOUT+1;
            end 
            else begin
                IF_ID_IR <= #2 MEM[PC];
                IF_ID_NPC <= #2 PC+1 ;
                PC <=  #2 PC+1;

            end
        end
    end


    always @(posedge clk2) begin // ID STAGE
        if(HALTED==0) begin
            ID_EX_A <= #2 (IF_ID_IR[25:21]==5'd0)?0:  REG[IF_ID_IR[25:21]]; // IVE WRITEN THIS DIFFERENTLY 
            ID_EX_B <= #2 (IF_ID_IR[20:16]==5'd0)?0:  REG[IF_ID_IR[20:16]];

            ID_EX_NPC <= #2 IF_ID_NPC;
            ID_EX_IR <= #2 IF_ID_IR;
            ID_EX_IMM <= #2 {{16{IF_ID_IR[15]}},IF_ID_IR[15:0]};// HE HAS USED EXTRA BRACKETS HERE;

            // UPDATE THE TYPE
            case (IF_ID_IR[31:26])
                ADD,SUB,AND,OR,SLT,MUL: ID_EX_TYPE <= #2 RR_ALU;
                ADDI,SUBI,SLTI: ID_EX_TYPE <= #2 RM_ALU;
                LW: ID_EX_TYPE <= #2 LOAD;
                SW: ID_EX_TYPE <= #2 STORE;
                BEQZ,BNEQZ:ID_EX_TYPE <= #2 BRANCH;
                HLT: ID_EX_TYPE <= #2 HALT;

                default: ID_EX_TYPE <= #2 HALT;
            endcase
        end
    end



    always @(posedge clk1 ) begin // EX STAGE
        if(HALTED==0) begin
            EX_MEM_IR <= #2 ID_EX_IR;
            EX_MEM_TYPE <= #2 ID_EX_TYPE;
            TAKEN_BRANCH <= #2 0;
            case(ID_EX_TYPE)
                RR_ALU:begin
                    case (ID_EX_IR[31:26])
                        ADD: EX_MEM_ALUOUT <= #2 ID_EX_A + ID_EX_B;
                        SUB: EX_MEM_ALUOUT <= #2 ID_EX_A - ID_EX_B;
                        AND: EX_MEM_ALUOUT <= #2 ID_EX_A & ID_EX_B;
                        OR: EX_MEM_ALUOUT <= #2 ID_EX_A | ID_EX_B;
                        MUL: EX_MEM_ALUOUT <= #2 ID_EX_A * ID_EX_B;
                        SLT: EX_MEM_ALUOUT <= #2 ID_EX_A < ID_EX_B;
                        default: EX_MEM_ALUOUT <= #2 32'hxxxxxxxx;
                    endcase
                end
                RM_ALU: begin
                    case (ID_EX_IR[31:26])
                        ADDI: EX_MEM_ALUOUT <= #2 ID_EX_A + ID_EX_IMM;
                        SUBI: EX_MEM_ALUOUT <= #2 ID_EX_A - ID_EX_IMM;
                        SLTI: EX_MEM_ALUOUT <= #2 ID_EX_A < ID_EX_IMM;
                        default: EX_MEM_ALUOUT <= #2 32'hxxxxxxxx;
                    endcase
                end
                LOAD,STORE:begin
                    EX_MEM_ALUOUT <= #2 ID_EX_A + ID_EX_IMM;
                    EX_MEM_B <= #2 ID_EX_B;
                end
                BRANCH:begin
                    EX_MEM_COND <= #2 (ID_EX_A == 0);
                    EX_MEM_ALUOUT <= #2 ID_EX_NPC+ID_EX_IMM;
                end
            endcase
        end
    end


    always @(posedge clk2) begin // MEM STAGE
        if(HALTED==0) begin
            MEM_WB_IR <= #2 EX_MEM_IR;
            MEM_WB_TYPE <= #2 EX_MEM_TYPE;
            case (EX_MEM_TYPE)
                RR_ALU,RM_ALU:begin
                    MEM_WB_ALUOUT <= #2 EX_MEM_ALUOUT;
                end 
                LOAD:begin
                    MEM_WB_LMD <= #2 MEM[EX_MEM_ALUOUT];
                end
                STORE:begin
                    if(TAKEN_BRANCH == 0)
                        MEM[EX_MEM_ALUOUT] <= #2 EX_MEM_B;
                end
                default: ;
            endcase
        end
    end


    always @(posedge clk1) begin //WB STAGE
        if(TAKEN_BRANCH == 0)begin
            case (MEM_WB_TYPE)
                RR_ALU: REG[MEM_WB_IR[15:11]] <= #2 MEM_WB_ALUOUT;
                RM_ALU: REG[MEM_WB_IR[20:16]] <= #2 MEM_WB_ALUOUT;
                LOAD: REG[MEM_WB_IR[20:16]] <= #2 MEM_WB_LMD;
                HALT: HALTED <= #2 1;
                default:; 
            endcase
        end
    end 
endmodule

tb2.v
`timescale 1ps/1ps
module tb2;

reg clk1,clk2;
integer k;

processor mips(clk1,clk2);

initial begin
    clk1=0;clk2=0;
    repeat(20)begin
        #5 clk1=1;#5 clk1=0;
        #5 clk2=1;#5 clk2=0;
    end
end

initial begin
    for(k=0;k<31;k=k+1)
        mips.REG[k]=0;

mips.MEM[0] = 32'h28010078;
mips.MEM[1] = 32'h0c631800;
mips.MEM[2] = 32'h20220000;
mips.MEM[3] = 32'h0c631800;
mips.MEM[4] = 32'h2842002d;
mips.MEM[5] = 32'h0c631800;
mips.MEM[6] = 32'h24220001;
mips.MEM[7] = 32'hfc000000;

mips.MEM[120]=90;
mips.HALTED=0;
mips.TAKEN_BRANCH=0;
mips.PC=0;
#500
$display("MEM[120]-%4d MEM[121]-%4d",mips.MEM[120],mips.MEM[121]);
end

initial begin
    $dumpfile("tb2.vcd");
    $dumpvars(0,tb2);
    #600 $finish;
end

endmodule

tb2.vcd
$date
	Sat Jan 31 20:05:44 2026
$end
$version
	Icarus Verilog
$end
$timescale
	1ps
$end
$scope module tb2 $end
$var reg 1 ! clk1 $end
$var reg 1 " clk2 $end
$var integer 32 # k [31:0] $end
$scope module mips $end
$var wire 1 ! clk1 $end
$var wire 1 " clk2 $end
$var parameter 6 $ ADD $end
$var parameter 6 % ADDI $end
$var parameter 6 & AND $end
$var parameter 6 ' BEQZ $end
$var parameter 6 ( BNEQZ $end
$var parameter 3 ) BRANCH $end
$var parameter 3 * HALT $end
$var parameter 6 + HLT $end
$var parameter 3 , LOAD $end
$var parameter 6 - LW $end
$var parameter 6 . MUL $end
$var parameter 6 / OR $end
$var parameter 3 0 RM_ALU $end
$var parameter 3 1 RR_ALU $end
$var parameter 6 2 SLT $end
$var parameter 6 3 SLTI $end
$var parameter 3 4 STORE $end
$var parameter 6 5 SUB $end
$var parameter 6 6 SUBI $end
$var parameter 6 7 SW $end
$var reg 32 8 EX_MEM_ALUOUT [31:0] $end
$var reg 32 9 EX_MEM_B [31:0] $end
$var reg 1 : EX_MEM_COND $end
$var reg 32 ; EX_MEM_IR [31:0] $end
$var reg 3 < EX_MEM_TYPE [2:0] $end
$var reg 1 = HALTED $end
$var reg 32 > ID_EX_A [31:0] $end
$var reg 32 ? ID_EX_B [31:0] $end
$var reg 32 @ ID_EX_IMM [31:0] $end
$var reg 32 A ID_EX_IR [31:0] $end
$var reg 32 B ID_EX_NPC [31:0] $end
$var reg 3 C ID_EX_TYPE [2:0] $end
$var reg 32 D IF_ID_IR [31:0] $end
$var reg 32 E IF_ID_NPC [31:0] $end
$var reg 32 F MEM_WB_ALUOUT [31:0] $end
$var reg 32 G MEM_WB_IR [31:0] $end
$var reg 32 H MEM_WB_LMD [31:0] $end
$var reg 3 I MEM_WB_TYPE [2:0] $end
$var reg 32 J PC [31:0] $end
$var reg 1 K TAKEN_BRANCH $end
$upscope $end
$upscope $end
$enddefinitions $end
$comment Show the parameter values. $end
$dumpall
b1001 7
b1011 6
b1 5
b11 4
b1100 3
b100 2
b0 1
b1 0
b11 /
b101 .
b1000 -
b10 ,
b111111 +
b101 *
b100 )
b1101 (
b1110 '
b10 &
b1010 %
b0 $
$end
#0
$dumpvars
0K
b0 J
bx I
bx H
bx G
bx F
bx E
bx D
bx C
bx B
bx A
bx @
bx ?
bx >
0=
bx <
bx ;
x:
bx 9
bx 8
b11111 #
0"
0!
$end
#5
1!
#7
b1 J
b1 E
b101000000000010000000001111000 D
#10
0!
#15
1"
#17
b1 C
b1111000 @
b101000000000010000000001111000 A
b1 B
b0 ?
b0 >
#20
0"
#25
1!
#27
b1111000 8
b1 <
b101000000000010000000001111000 ;
b10 J
b10 E
b1100011000110001100000000000 D
#30
0!
#35
1"
#37
b1111000 F
b1 I
b101000000000010000000001111000 G
b0 C
b1100000000000 @
b1100011000110001100000000000 A
b10 B
#40
0"
#45
1!
#47
b11 J
b11 E
b100000001000100000000000000000 D
b0 8
b0 <
b1100011000110001100000000000 ;
#50
0!
#55
1"
#57
b10 C
b0 @
b100000001000100000000000000000 A
b11 B
b1111000 >
b0 F
b0 I
b1100011000110001100000000000 G
#60
0"
#65
1!
#67
b0 9
b1111000 8
b10 <
b100000001000100000000000000000 ;
b100 J
b100 E
b1100011000110001100000000000 D
#70
0!
#75
1"
#77
b1011010 H
b10 I
b100000001000100000000000000000 G
b0 C
b1100000000000 @
b1100011000110001100000000000 A
b100 B
b0 >
#80
0"
#85
1!
#87
b101 J
b101 E
b101000010000100000000000101101 D
b0 8
b0 <
b1100011000110001100000000000 ;
#90
0!
#95
1"
#97
b1 C
b101101 @
b101000010000100000000000101101 A
b101 B
b1011010 ?
b1011010 >
b0 I
b1100011000110001100000000000 G
#100
0"
#105
1!
#107
b10000111 8
b1 <
b101000010000100000000000101101 ;
b110 J
b110 E
b1100011000110001100000000000 D
#110
0!
#115
1"
#117
b10000111 F
b1 I
b101000010000100000000000101101 G
b0 C
b1100000000000 @
b1100011000110001100000000000 A
b110 B
b0 ?
b0 >
#120
0"
#125
1!
#127
b111 J
b111 E
b100100001000100000000000000001 D
b0 8
b0 <
b1100011000110001100000000000 ;
#130
0!
#135
1"
#137
b11 C
b1 @
b100100001000100000000000000001 A
b111 B
b10000111 ?
b1111000 >
b0 F
b0 I
b1100011000110001100000000000 G
#140
0"
#145
1!
#147
b10000111 9
b1111001 8
b11 <
b100100001000100000000000000001 ;
b1000 J
b1000 E
b11111100000000000000000000000000 D
#150
0!
#155
1"
#157
b11 I
b100100001000100000000000000001 G
b101 C
b0 @
b11111100000000000000000000000000 A
b1000 B
b0 ?
b0 >
#160
0"
#165
1!
#167
b1001 J
b1001 E
bx D
b101 <
b11111100000000000000000000000000 ;
#170
0!
#175
1"
#177
bx @
bx A
b1001 B
bx ?
bx >
b101 I
b11111100000000000000000000000000 G
#180
0"
#185
1!
#187
1=
bx ;
b1010 J
b1010 E
